gordon_gcp/__init__.py
gordon_gcp/exceptions.py
gordon_gcp/clients/__init__.py
gordon_gcp/clients/_utils.py
gordon_gcp/clients/auth.py
gordon_gcp/clients/gce.py
gordon_gcp/clients/gcrm.py
gordon_gcp/clients/gdns.py
gordon_gcp/clients/http.py
gordon_gcp/plugins/__init__.py
gordon_gcp/plugins/_utils.py
gordon_gcp/plugins/janitor/__init__.py
gordon_gcp/plugins/janitor/authority.py
gordon_gcp/plugins/janitor/gpubsub_publisher.py
gordon_gcp/plugins/janitor/reconciler.py
gordon_gcp/plugins/service/__init__.py
gordon_gcp/plugins/service/enricher.py
gordon_gcp/plugins/service/event_consumer.py
gordon_gcp/plugins/service/gdns_publisher.py
gordon_gcp/schema/__init__.py
gordon_gcp/schema/parse.py
gordon_gcp/schema/validate.py
gordon_gcp/schema/examples/audit-log.first-operation.json
gordon_gcp/schema/examples/audit-log.last-operation.json
gordon_gcp/schema/examples/audit-log.no-operation.json
gordon_gcp/schema/examples/event.A.json
gordon_gcp/schema/examples/event.CNAME.json
gordon_gcp/schema/examples/event.NS.json
gordon_gcp/schema/schemas/audit-log.schema.json
gordon_gcp/schema/schemas/event.schema.json
gordon_dns_gcp-0.0.1.dev38.dist-info/LICENSE
gordon_dns_gcp-0.0.1.dev38.dist-info/METADATA
gordon_dns_gcp-0.0.1.dev38.dist-info/WHEEL
gordon_dns_gcp-0.0.1.dev38.dist-info/entry_points.txt
gordon_dns_gcp-0.0.1.dev38.dist-info/top_level.txt
gordon_dns_gcp-0.0.1.dev38.dist-info/RECORD
