Metadata-Version: 2.1
Name: gordon-dns-gcp
Version: 0.0.1.dev38
Summary: GCP Plugins for Gordon and Gordon Janitor
Home-page: https://github.com/spotify/gordon-gcp
Author: Lynn Root
Author-email: lynn@spotify.com
Maintainer: Lynn Root
Maintainer-email: lynn@spotify.com
License: Apache 2.0
Keywords: dns,gcp,gce,pubsubgoogle cloud platform
Platform: UNKNOWN
Classifier: Development Status :: 1 - Planning
Classifier: License :: OSI Approved :: Apache Software License
Classifier: Natural Language :: English
Classifier: Operating System :: POSIX :: Linux
Classifier: Operating System :: MacOS :: MacOS X
Classifier: Programming Language :: Python
Classifier: Programming Language :: Python :: 3
Classifier: Programming Language :: Python :: 3.6
Classifier: Programming Language :: Python :: Implementation :: CPython
Classifier: Programming Language :: Python :: Implementation :: PyPy
Classifier: Topic :: Internet :: Name Service (DNS)
Requires-Dist: aiohttp
Requires-Dist: asyncio-extras
Requires-Dist: google-api-core
Requires-Dist: google-auth
Requires-Dist: google-cloud-pubsub
Requires-Dist: gordon-dns
Requires-Dist: gordon-janitor
Requires-Dist: jsonschema
Requires-Dist: zope.interface
